{
  "parent": "quest_giver:quest_0060_01b",
  "reputation": 0,
  "icon": "minecraft:oak_boat",
  "start": {
    "title": {
      "text": "보트 제작"
    },
    "description": {
      "text": "잊지 말게, 보트는 반드시 $(red)마름병 발사나무$()로 만들어야 하네."
    }
  },
  "complete": {
    "title": {
      "text": "고맙네!"
    },
    "description": {
      "text": "그럭저럭 쓸만하구먼, 손볼 곳이 좀 보이긴 하네만. 뭐, 이 정도면 충분하네. 고맙구먼. 여기 보상일세, 자네 마음에 들 게야."
    }
  },
  "tasks": [
    {
      "item": {
        "item": "biomemakeover:blighted_balsa_boat"
      },
      "id": "quest_giver:gift",
      "times": 1
    }
  ],
  "rewards": [
    {
      "command": "/advancement grant @p only custom:trade_fisherman",
      "id": "quest_giver:command"
    },
    {
      "command": "/addreputation reputation:villager @p 3",
      "id": "quest_giver:command"
    },
    {
      "item": {
        "item": "paraglider:spirit_orb"
      },
      "id": "quest_giver:item",
      "times": 1
    }
  ]
}